{
  "coord": {
    "lon": -0.1257,
    "lat": 51.5085
  },
  "weather": [
    {
      "id": 800,
      "main": "Clear",
      "description": "clear sky",
      "icon": "01n"
    }
  ],
  "base": "stations",
  "main": {
    "temp": 4.44,
    "feels_like": 4.44,
    "temp_min": 2.98,
    "temp_max": 5.95,
    "pressure": 1014,
    "humidity": 94,
    "sea_level": 1014,
    "grnd_level": 1010
  },
  "visibility": 10000,
  "wind": {
    "speed": 0.51,
    "deg": 0
  },
  "clouds": {
    "all": 1
  },
  "dt": 1766211206,
  "sys": {
    "type": 2,
    "id": 2075535,
    "country": "GB",
    "sunrise": 1766217801,
    "sunset": 1766245973
  },
  "timezone": 0,
  "id": 2643743,
  "name": "London",
  "cod": 200,
  "_last_updated_utc": "2025-12-20T06:22:03.144Z"
}