{
  "coord": {
    "lon": -0.1257,
    "lat": 51.5085
  },
  "weather": [
    {
      "id": 800,
      "main": "Clear",
      "description": "clear sky",
      "icon": "01n"
    }
  ],
  "base": "stations",
  "main": {
    "temp": 10.14,
    "feels_like": 9.17,
    "temp_min": 8.47,
    "temp_max": 11.66,
    "pressure": 1027,
    "humidity": 75,
    "sea_level": 1027,
    "grnd_level": 1024
  },
  "visibility": 10000,
  "wind": {
    "speed": 4.63,
    "deg": 100
  },
  "clouds": {
    "all": 0
  },
  "dt": 1776974785,
  "sys": {
    "type": 2,
    "id": 2075535,
    "country": "GB",
    "sunrise": 1776919690,
    "sunset": 1776971350
  },
  "timezone": 3600,
  "id": 2643743,
  "name": "London",
  "cod": 200,
  "_last_updated_utc": "2026-04-23T20:19:26.389Z"
}