{
  "coord": {
    "lon": -0.1257,
    "lat": 51.5085
  },
  "weather": [
    {
      "id": 804,
      "main": "Clouds",
      "description": "overcast clouds",
      "icon": "04n"
    }
  ],
  "base": "stations",
  "main": {
    "temp": 10.75,
    "feels_like": 10.15,
    "temp_min": 10.75,
    "temp_max": 10.75,
    "pressure": 1017,
    "humidity": 87,
    "sea_level": 1017,
    "grnd_level": 1013
  },
  "visibility": 10000,
  "wind": {
    "speed": 3.94,
    "deg": 222,
    "gust": 10.26
  },
  "clouds": {
    "all": 100
  },
  "dt": 1776315012,
  "sys": {
    "country": "GB",
    "sunrise": 1776315767,
    "sunset": 1776365847
  },
  "timezone": 3600,
  "id": 2643743,
  "name": "London",
  "cod": 200,
  "_last_updated_utc": "2026-04-16T05:00:25.730Z"
}