{
  "coord": {
    "lon": -0.1257,
    "lat": 51.5085
  },
  "weather": [
    {
      "id": 800,
      "main": "Clear",
      "description": "clear sky",
      "icon": "01d"
    }
  ],
  "base": "stations",
  "main": {
    "temp": 16.01,
    "feels_like": 14.82,
    "temp_min": 16.01,
    "temp_max": 16.01,
    "pressure": 1025,
    "humidity": 44,
    "sea_level": 1025,
    "grnd_level": 1021
  },
  "visibility": 10000,
  "wind": {
    "speed": 6.84,
    "deg": 80,
    "gust": 9.81
  },
  "clouds": {
    "all": 2
  },
  "dt": 1776859962,
  "sys": {
    "country": "GB",
    "sunrise": 1776833413,
    "sunset": 1776884850
  },
  "timezone": 3600,
  "id": 2643743,
  "name": "London",
  "cod": 200,
  "_last_updated_utc": "2026-04-22T12:20:37.913Z"
}