{
  "coord": {
    "lon": -0.1257,
    "lat": 51.5085
  },
  "weather": [
    {
      "id": 801,
      "main": "Clouds",
      "description": "few clouds",
      "icon": "02n"
    }
  ],
  "base": "stations",
  "main": {
    "temp": 19.77,
    "feels_like": 19.26,
    "temp_min": 18.34,
    "temp_max": 20.57,
    "pressure": 1016,
    "humidity": 56,
    "sea_level": 1016,
    "grnd_level": 1013
  },
  "visibility": 10000,
  "wind": {
    "speed": 2.68,
    "deg": 315,
    "gust": 4.02
  },
  "clouds": {
    "all": 18
  },
  "dt": 1780258351,
  "sys": {
    "type": 2,
    "id": 2075535,
    "country": "GB",
    "sunrise": 1780199407,
    "sunset": 1780257994
  },
  "timezone": 3600,
  "id": 2643743,
  "name": "London",
  "cod": 200,
  "_last_updated_utc": "2026-05-31T20:24:03.711Z"
}