{
  "coord": {
    "lon": -0.1257,
    "lat": 51.5085
  },
  "weather": [
    {
      "id": 804,
      "main": "Clouds",
      "description": "overcast clouds",
      "icon": "04n"
    }
  ],
  "base": "stations",
  "main": {
    "temp": 5.81,
    "feels_like": 3.42,
    "temp_min": 5.31,
    "temp_max": 6.27,
    "pressure": 997,
    "humidity": 92,
    "sea_level": 997,
    "grnd_level": 994
  },
  "visibility": 9000,
  "wind": {
    "speed": 3.09,
    "deg": 40
  },
  "clouds": {
    "all": 100
  },
  "dt": 1769378727,
  "sys": {
    "type": 2,
    "id": 2075535,
    "country": "GB",
    "sunrise": 1769327336,
    "sunset": 1769358981
  },
  "timezone": 0,
  "id": 2643743,
  "name": "London",
  "cod": 200,
  "_last_updated_utc": "2026-01-25T22:15:00.965Z"
}