{
  "coord": {
    "lon": -0.1257,
    "lat": 51.5085
  },
  "weather": [
    {
      "id": 800,
      "main": "Clear",
      "description": "clear sky",
      "icon": "01d"
    }
  ],
  "base": "stations",
  "main": {
    "temp": 32.71,
    "feels_like": 33.13,
    "temp_min": 30.99,
    "temp_max": 34.06,
    "pressure": 1029,
    "humidity": 39,
    "sea_level": 1029,
    "grnd_level": 1025
  },
  "visibility": 10000,
  "wind": {
    "speed": 2.68,
    "deg": 175,
    "gust": 6.26
  },
  "clouds": {
    "all": 5
  },
  "dt": 1779720908,
  "sys": {
    "type": 2,
    "id": 268730,
    "country": "GB",
    "sunrise": 1779681359,
    "sunset": 1779739152
  },
  "timezone": 3600,
  "id": 2643743,
  "name": "London",
  "cod": 200,
  "_last_updated_utc": "2026-05-25T15:01:37.157Z"
}